whirls.py
whirls-1.2.dist-info/DESCRIPTION.rst
whirls-1.2.dist-info/METADATA
whirls-1.2.dist-info/RECORD
whirls-1.2.dist-info/WHEEL
whirls-1.2.dist-info/entry_points.txt
whirls-1.2.dist-info/metadata.json
whirls-1.2.dist-info/top_level.txt
