Metadata-Version: 2.0
Name: whirls
Version: 1.2
Summary: A fullscreen program that displays an animated, twisting tessellation of whirls.
Home-page: https://bitbucket.org/David_Nickerson/whirls
Author: David Nickerson
Author-email: UNKNOWN
License: GPLv3+
Keywords: curve derived polygon pursuit spiral whirl
Platform: UNKNOWN
Classifier: Development Status :: 4 - Beta
Classifier: Intended Audience :: End Users/Desktop
Classifier: License :: OSI Approved :: GNU General Public License v3 or later (GPLv3+)
Classifier: Natural Language :: English
Classifier: Programming Language :: Python :: 3.5
Classifier: Topic :: Games/Entertainment :: Simulation
Requires-Dist: matplotlib
Requires-Dist: numpy
Requires-Dist: pgu
Requires-Dist: pygame
Requires-Dist: scipy
